project_home_tags/__init__.py
project_home_tags/apps.py
project_home_tags/templatetags/__init__.py
project_home_tags/templatetags/project_home.py
django_project_home_templatetags-0.2.1.dist-info/LICENSE
django_project_home_templatetags-0.2.1.dist-info/METADATA
django_project_home_templatetags-0.2.1.dist-info/WHEEL
django_project_home_templatetags-0.2.1.dist-info/top_level.txt
django_project_home_templatetags-0.2.1.dist-info/RECORD
